ct_mail_handler/__init__.py
ct_mail_handler/mail_handler.py
ct_mail_handler/models.py
ct_mail_handler-0.0.2.dist-info/METADATA
ct_mail_handler-0.0.2.dist-info/WHEEL
ct_mail_handler-0.0.2.dist-info/top_level.txt
ct_mail_handler-0.0.2.dist-info/RECORD
