Metadata-Version: 2.4
Name: ct_mail_handler
Version: 0.0.2
Summary: Custom mail function and middleware to send logs to a mail server
Author: Shatrugna Rao Korukanti
Author-email: shatrugna_korukanti@tecnics.com
License: MIT
Classifier: Development Status :: 3 - Alpha
Classifier: Intended Audience :: Developers
Classifier: Operating System :: OS Independent
Classifier: Programming Language :: Python :: 3
Classifier: Topic :: Software Development :: Libraries :: Python Modules
Requires-Dist: requests
Dynamic: author
Dynamic: author-email
Dynamic: classifier
Dynamic: description
Dynamic: description-content-type
Dynamic: license
Dynamic: requires-dist
Dynamic: summary
